pyotheus-0.1.0.dev3.dist-info/METADATA
pyotheus-0.1.0.dev3.dist-info/WHEEL
pyotheus-0.1.0.dev3.dist-info/licenses/LICENSE
pyotheus/__init__.py
pyotheus/__init__.pyi
pyotheus/py.typed
pyotheus/pyotheus.abi3.so
pyotheus-0.1.0.dev3.dist-info/RECORD
